{
	"name": "CebollaFinal",
	"plugin-id": "Sprite",
	"sid": 604820153316336,
	"isGlobal": false,
	"editorNewInstanceIsReplica": true,
	"instanceVariables": [],
	"behaviorTypes": [],
	"effectTypes": [],
	"animations": {
		"items": [
			{
				"frames": [
					{
						"width": 250,
						"height": 250,
						"originX": 0.5,
						"originY": 0.5,
						"originalSource": "",
						"exportFormat": "lossless",
						"exportQuality": 0.8,
						"fileType": "image/png",
						"imageSpriteId": 96993,
						"collisionPoly": {
							"points": [
								0.5,
								0.096,
								0.544,
								0.096,
								0.596,
								0.116,
								0.616,
								0.216,
								0.52,
								0.232,
								0.444,
								0.228,
								0.364,
								0.148,
								0.444,
								0.1
							]
						},
						"useCollisionPoly": true,
						"duration": 1,
						"tag": ""
					}
				],
				"sid": 560545664352573,
				"name": "Animation 1",
				"isLooping": false,
				"isPingPong": false,
				"repeatCount": 1,
				"repeatTo": 0,
				"speed": 5
			}
		],
		"subfolders": []
	}
}